graphpack/__init__.py
graphpack/compression.py
graphpack/utils.py
graphpack/config/additional_js
graphpack/config/additional_js_old
graphpack/config/const_options
graphpack/config/physics_options_big
graphpack/config/physics_options_small
graphpack/config/style_options
graphpack/demo/demo.py
graphpack/demo/sankey.py
graphpack-0.1.2.dist-info/LICENSE
graphpack-0.1.2.dist-info/METADATA
graphpack-0.1.2.dist-info/WHEEL
graphpack-0.1.2.dist-info/entry_points.txt
graphpack-0.1.2.dist-info/top_level.txt
graphpack-0.1.2.dist-info/RECORD
