Metadata-Version: 2.1
Name: graphpack
Version: 0.1.2
Summary: A Python tool to perform graph compression and visualization
Author: Bottazzi Daniele
Author-email: daniele.bottazzi@mail.polimi.it
License: MIT
Classifier: Programming Language :: Python :: 3
Classifier: License :: OSI Approved :: MIT License
Classifier: Operating System :: OS Independent
Requires-Python: >=3.6
License-File: LICENSE
Requires-Dist: matplotlib ~=3.6.3
Requires-Dist: networkx ~=2.8.8
Requires-Dist: numpy ~=1.26.2
Requires-Dist: pandas ~=2.2.1
Requires-Dist: gseapy ~=1.1.0
Requires-Dist: gensim ~=4.3.2
Requires-Dist: scikit-learn ~=1.4.1.post1
Requires-Dist: msgpack ~=1.0.7
Requires-Dist: cvxpy ~=1.5.1
Requires-Dist: tqdm ~=4.66.1
Requires-Dist: community ~=1.0.0b1
Requires-Dist: python-louvain ~=0.16
Requires-Dist: node2vec ~=0.4.6
Requires-Dist: requests ~=2.31.0
Requires-Dist: pyvis ~=0.3.1
Requires-Dist: dash ~=2.17.1
Requires-Dist: dash-cytoscape ~=1.0.1
Requires-Dist: plotly ~=5.22.0
Requires-Dist: seaborn ~=0.12.2
